Rationale/__init__.py
Rationale/rationale.py
rationale-0.0.1.dist-info/METADATA
rationale-0.0.1.dist-info/WHEEL
rationale-0.0.1.dist-info/licenses/LICENSE
rationale-0.0.1.dist-info/RECORD
